src/tools.v
// ASSERT is a non blocking test function.
`define ASSERT(condition, name, message) \
    if (condition) begin \
        $display("✅ PASS TEST '%s'", name); \
    end else begin \
        $display("❌ ERROR TEST '%s': %s", name, message); \
    end

src/specs.vh
`ifndef SPECS_VH
`define SPECS_VH

// supported opcodes
`define OP_SUM  3'b000
`define OP_SUB  3'b001
`define OP_AND  3'b010
`define OP_XOR  3'b011
`define OP_NOP  3'b100

// supported cpu bit width
`define WORD 8
`define OP_WIDTH 3

// opcode map
function string opname;
    input [`OP_WIDTH-1:0] op;
    case(op)
        `OP_SUM: opname = "SUM";
        `OP_SUB: opname = "SUB";
        `OP_AND: opname = "AND";
        `OP_XOR: opname = "XOR";
        default: opname = "???";
    endcase
endfunction

`endif // SPECS_VH

src/alu/alu.v
`timescale 1ns/1ps
`include "specs.vh"

module alu #(
    parameter WIDTH = `WORD,
    parameter OP_WIDTH = `OP_WIDTH
)(
    input wire [WIDTH-1:0] i_a,
    input wire [WIDTH-1:0] i_b,
    input wire [OP_WIDTH-1:0] i_opcode,

    output wire [WIDTH-1:0] o_result,
    output wire o_zero,
    output wire o_cf
);

reg [WIDTH-1:0] r_result;
wire [WIDTH+1-1:0] extended_sum = {1'b0, i_a} + {1'b0, i_b};
// wire [WIDTH+1-1:0] extended_sub = {1'b0, i_a} - {1'b0, i_b}; 

assign o_zero = (r_result == 0);
assign o_cf = (i_opcode == `OP_SUM)  ? extended_sum[WIDTH]   :  
              (i_opcode == `OP_SUB)  ? (i_a < i_b)       : 1'b0;
assign o_result = r_result;

always_comb begin
    case(i_opcode)
        `OP_SUM: r_result = i_a + i_b;
        `OP_SUB: r_result = i_a - i_b;
        `OP_AND: r_result = i_a & i_b;
        `OP_XOR: r_result = i_a ^ i_b;
        default: r_result = 0;
    endcase
end

endmodule

src/control_unit.v
// Instructions to support 

// R-type: Register-register ALU operation; rd = rs1 op rs2
// Example: add x5, x1, x2  // x5 = x1 + x2

// I-type: ALU with immediate or load; rd = rs1 op imm
// Example: addi x6, x3, 10 // x6 = x3 + 10

// S-type: Store to memory; Mem[rs1 + imm] = rs2
// Example: sw x4, 16(x7)   // Store x4 at address x7+16

// B-type: Conditional branch; if (rs1 op rs2) pc += imm
// Example: beq x8, x9, 20  // Branch if x8 == x9 to PC+20

// U-type: Loads upper immediate to rd
// Example: lui x10, 0x1000 // x10 = 0x10000000

// J-type: Jump and link; rd = PC+4; PC += imm
// Example: jal x1, 100     // Jump to PC+100, save return in x1

module control_unit #(
    parameter OP_WIDTH = 3,
    parameter OP_TYPE = 3'b000
)(
    input wire [OP_WIDTH-1:0] opcode,
    output reg is_reg_write,
    output reg alu_src_type,
    output reg [OP_WIDTH-1:0] alu_op
);

always_comb begin
    case (opcode) 
        `OP_SUM, `OP_SUB, `OP_AND, `OP_XOR: begin
            is_reg_write = `WR_EN;
            alu_src_type = `R_TYPE; // source B is register
            alu_op = opcode;
        end
        3'b100: begin // example I-type opcode
            is_reg_write = `WR_DISEN;
            alu_src_type = `NOT_R_TYPE;         // source B is immediate
            alu_op = `OP_SUM;    // typically immediate ops use SUM logic
        end
        default: begin
            is_reg_write = `WR_DISEN;
            alu_src_type = `NOT_R_TYPE;
            alu_op = `OP_NOP;
        end
    endcase 
end

endmodule

src/register_file/register_file.v
`timescale 1ns/1ps
`include "specs.vh"

// specs:
// - 32 registers (inspired by RISC-V)
// - 5 bit address space (log2(32))

module register_file #(
    parameter WIDTH = `WORD,
    parameter ZERO_REGISTER = 5'b00000,
    parameter ADDR_SPACE = `REG_ADDRESS_SPACE,
    parameter REG_AMOUNT = 32
)(
    input wire clk,
    input wire rst,
    input wire [ADDR_SPACE-1:0] r1_addr,
    input wire [ADDR_SPACE-1:0] r2_addr,
    input wire [ADDR_SPACE-1:0] wr_addr,
    input wire wr_en,
    input wire [WIDTH-1:0] wr_data,
    output reg [WIDTH-1:0] r1_data,
    output reg [WIDTH-1:0] r2_data
);

reg [WIDTH-1:0] registers [0:REG_AMOUNT-1];

always @(posedge clk or posedge rst) begin
    if (rst) begin
        integer i;
        for (i = 0; i < REG_AMOUNT; i = i + 1) begin
            registers[i] <= 0;
        end 
    end else begin
        if (wr_en && (wr_addr != ZERO_REGISTER)) begin
            registers[wr_addr] <= wr_data;
        end
        registers[ZERO_REGISTER] <= 0;
    end
end

always_comb begin
    r1_data = (r1_addr == ZERO_REGISTER) ? 0 : registers[r1_addr];
    r2_data = (r2_addr == ZERO_REGISTER) ? 0 : registers[r2_addr];
end

endmodule

src/rom.v


module rom #(
    parameter DATA_WIDTH = 32,
    parameter ADDR_WIDTH = 4
)(
    input wire [ADDR_WIDTH-1:0] addr,
    output reg [DATA_WIDTH-1:0] r_data
);

reg [DATA_WIDTH-1:0] rom [0:15];



initial begin
        rom[0] = 32'h00000013;
        rom[1] = 32'h000101B3;
        rom[2] = 32'h00018233;
        rom[3] = 32'h000202B3;
        rom[4] = 32'h00028333;
        rom[5] = 32'h000303B3;
        rom[6] = 32'h00038433;
        rom[7] = 32'h000404B3;
        rom[8] = 32'h00048533;
        rom[9] = 32'h000505B3;
        rom[10] = 32'h00058633;
        rom[11] = 32'h000606B3;
        rom[12] = 32'h00068733;
        rom[13] = 32'h000707B3;
        rom[14] = 32'h00078833;
        rom[15] = 32'h000808B3;
end

always_comb begin
    r_data = rom[addr];
end


endmodule

src/pc.v
module pc #(
    parameter WIDTH = 4
)(
    input wire clk,
    input wire rst,
    input wire [WIDTH-1:0] next_pc,
    output reg [WIDTH-1:0] current_pc
);

always @(posedge clk or posedge rst) begin
    if (rst) begin
        current_pc <= 0;
    end else begin
        current_pc <= next_pc; 
    end
end

endmodule

src/cpu.v
`include "specs.vh"

// Top-level CPU module integrating all components
module cpu #(
    parameter OP_WIDTH = `OP_WIDTH,
    parameter PC_WIDTH = `INS_ADDRESS_SPACE,
    parameter INSTR_WIDTH = `INS_WIDTH,
    parameter DATA_WIDTH = `WORD,
    parameter ADDR_SPACE = `REG_ADDRESS_SPACE
)(
    input wire clk,
    input wire rst
);

// Program Counter signals
wire [PC_WIDTH-1:0] pc_next;
reg [PC_WIDTH-1:0] pc_current;

// Calculate next PC (simple increment for now, no branches)
assign pc_next = pc_current + 1;

// Single instruction fetched from ROM
wire [INSTR_WIDTH-1:0] instruction;

// Instruction field slicing (RISC-V format)
wire [6:0] funct7 = instruction[31:25];
wire [4:0] rs2 = instruction[24:20];
wire [4:0] rs1 = instruction[19:15];
wire [2:0] funct3 = instruction[14:12];
wire [4:0] rd = instruction[11:7];
wire [6:0] opcode = instruction[6:0];

// For now, we'll use funct3 as our simple opcode
// This is simplified - real RISC-V uses opcode + funct3 + funct7
wire [2:0] simple_opcode = funct3;

// Control signals from control unit
wire reg_write;
wire alu_src; 
wire [2:0] alu_op;

// Register file data signals
wire [DATA_WIDTH-1:0] rs1_data;
wire [DATA_WIDTH-1:0] rs2_data;

// ALU signals
wire [DATA_WIDTH-1:0] alu_in_b; // MUX between register and immediate
wire [DATA_WIDTH-1:0] alu_result;
wire alu_zero, alu_cf;

// Immediate value extraction (I-type format: sign-extended 12 bits)
// For now, we'll just extract the I-type immediate
wire [DATA_WIDTH-1:0] imm = {{20{instruction[31]}}, instruction[31:20]};

// MUX for ALU input B: select register or immediate
assign alu_in_b = alu_src ? imm : rs2_data;

// Program Counter instance
pc #(
    .WIDTH(PC_WIDTH)
) pc_inst(
    .clk(clk),
    .rst(rst),
    .next_pc(pc_next), 
    .current_pc(pc_current) 
);

// ROM instance (instruction memory)
rom #(
    .ADDR_WIDTH(PC_WIDTH),
    .DATA_WIDTH(INSTR_WIDTH)
) rom_inst(
    .addr(pc_current),
    .r_data(instruction)
);

// Register file instance
register_file #(
    .WIDTH(DATA_WIDTH),
    .ADDR_SPACE(ADDR_SPACE)
) rf_inst (
    .clk(clk),
    .rst(rst),
    .r1_addr(rs1),
    .r2_addr(rs2),
    .wr_addr(rd),
    .wr_en(reg_write),
    .wr_data(alu_result),
    .r1_data(rs1_data),
    .r2_data(rs2_data)
);

// Control unit instance
control_unit #(
    .OP_WIDTH(3)
) cunit(
    .opcode(simple_opcode),
    .is_reg_write(reg_write),
    .alu_src_type(alu_src), // 0 = register, 1 = immediate
    .alu_op(alu_op)
);

// ALU instance
alu #(
    .WIDTH(DATA_WIDTH),
    .OP_WIDTH(3)
) alu_inst(
    .i_a(rs1_data),
    .i_b(alu_in_b), // MUXed: immediate or register data
    .i_opcode(alu_op),
    .o_result(alu_result),
    .o_zero(alu_zero),
    .o_cf(alu_cf)
);

endmodule

src/cpu_test.v
`timescale 1ns/1ps
`include "specs.vh"
`include "tools.v"

module cpu_test;

reg clk;
reg rst;

// Instantiate CPU
cpu cpu_inst(
    .clk(clk),
    .rst(rst)
);

// Clock generation
initial begin
    clk = 0;
    forever #5 clk = ~clk; // 10ns period = 100MHz
end

// Test stimulus
initial begin
    $dumpfile("cpu_test.vcd");
    $dumpvars(0, cpu_test);
    
    // Reset
    rst = 1;
    #20;
    rst = 0;
    
    // Let CPU run for several clock cycles
    // The ROM contains add instructions that should execute
    #200;
    
    // Check that some registers have been written
    // The ROM has instructions like: add x3, x1, x2
    // Since registers start at 0, and we're adding 0+0, results will be 0
    // But we can verify the CPU is running by checking PC progression
    
    $display("=== CPU Test Complete ===");
    $display("Final PC: %d", cpu_inst.pc_current);
    
    // Basic sanity check - PC should have advanced
    `ASSERT(cpu_inst.pc_current > 0, "CPU PC advanced", "PC should increment from 0");
    
    // Check that register file is responsive
    // After reset, all registers should be 0
    `ASSERT(cpu_inst.rf_inst.registers[0] == 0, "Register x0 is zero", "x0 must always be zero");
    
    $display("✅ CPU basic functionality test passed");
    
    $finish;
end

// Monitor for debugging
initial begin
    $monitor("Time=%0t | PC=%d | Instruction=%h | rs1=%d rs2=%d rd=%d | ALU_op=%b | Result=%h", 
             $time, cpu_inst.pc_current, cpu_inst.instruction, 
             cpu_inst.rs1, cpu_inst.rs2, cpu_inst.rd,
             cpu_inst.alu_op, cpu_inst.alu_result);
end

endmodule

src/cpu_test.vcd
$date
	Fri Jan  9 16:42:50 2026
$end
$version
	Icarus Verilog
$end
$timescale
	1ps
$end
$scope module cpu_test $end
$var reg 1 ! clk $end
$var reg 1 " rst $end
$scope module cpu_inst $end
$var wire 1 ! clk $end
$var wire 1 " rst $end
$var wire 3 # simple_opcode [2:0] $end
$var wire 32 $ rs2_data [31:0] $end
$var wire 5 % rs2 [4:0] $end
$var wire 32 & rs1_data [31:0] $end
$var wire 5 ' rs1 [4:0] $end
$var wire 1 ( reg_write $end
$var wire 5 ) rd [4:0] $end
$var wire 4 * pc_next [3:0] $end
$var wire 4 + pc_current [3:0] $end
$var wire 7 , opcode [6:0] $end
$var wire 32 - instruction [31:0] $end
$var wire 32 . imm [31:0] $end
$var wire 7 / funct7 [6:0] $end
$var wire 3 0 funct3 [2:0] $end
$var wire 1 1 alu_zero $end
$var wire 1 2 alu_src $end
$var wire 32 3 alu_result [31:0] $end
$var wire 3 4 alu_op [2:0] $end
$var wire 32 5 alu_in_b [31:0] $end
$var wire 1 6 alu_cf $end
$var parameter 32 7 ADDR_SPACE $end
$var parameter 32 8 DATA_WIDTH $end
$var parameter 32 9 INSTR_WIDTH $end
$var parameter 32 : OP_WIDTH $end
$var parameter 32 ; PC_WIDTH $end
$scope module alu_inst $end
$var wire 32 < i_b [31:0] $end
$var wire 32 = o_result [31:0] $end
$var wire 1 1 o_zero $end
$var wire 1 6 o_cf $end
$var wire 3 > i_opcode [2:0] $end
$var wire 32 ? i_a [31:0] $end
$var wire 33 @ extended_sum [32:0] $end
$var parameter 32 A OP_WIDTH $end
$var parameter 32 B WIDTH $end
$var reg 32 C r_result [31:0] $end
$upscope $end
$scope module cunit $end
$var wire 3 D opcode [2:0] $end
$var parameter 3 E OP_TYPE $end
$var parameter 32 F OP_WIDTH $end
$var reg 3 G alu_op [2:0] $end
$var reg 1 2 alu_src_type $end
$var reg 1 ( is_reg_write $end
$upscope $end
$scope module pc_inst $end
$var wire 1 ! clk $end
$var wire 4 H next_pc [3:0] $end
$var wire 1 " rst $end
$var parameter 32 I WIDTH $end
$var reg 4 J current_pc [3:0] $end
$upscope $end
$scope module rf_inst $end
$var wire 1 ! clk $end
$var wire 5 K r1_addr [4:0] $end
$var wire 5 L r2_addr [4:0] $end
$var wire 1 " rst $end
$var wire 5 M wr_addr [4:0] $end
$var wire 32 N wr_data [31:0] $end
$var wire 1 ( wr_en $end
$var parameter 32 O ADDR_SPACE $end
$var parameter 32 P REG_AMOUNT $end
$var parameter 32 Q WIDTH $end
$var parameter 5 R ZERO_REGISTER $end
$var reg 32 S r1_data [31:0] $end
$var reg 32 T r2_data [31:0] $end
$scope begin $unm_blk_14 $end
$var integer 32 U i [31:0] $end
$upscope $end
$upscope $end
$scope module rom_inst $end
$var wire 4 V addr [3:0] $end
$var parameter 32 W ADDR_WIDTH $end
$var parameter 32 X DATA_WIDTH $end
$var reg 32 Y r_data [31:0] $end
$upscope $end
$upscope $end
$upscope $end
$enddefinitions $end
$comment Show the parameter values. $end
$dumpall
b100000 X
b100 W
b0 R
b100000 Q
b100000 P
b101 O
b100 I
b11 F
b0 E
b100000 B
b11 A
b100 ;
b110 :
b100000 9
b100000 8
b101 7
$end
#0
$dumpvars
b10011 Y
b0 V
b100000 U
b0 T
b0 S
b0 N
b0 M
b0 L
b0 K
b0 J
b1 H
b0 G
b0 D
b0 C
b0 @
b0 ?
b0 >
b0 =
b0 <
06
b0 5
b0 4
b0 3
02
11
b0 0
b0 /
b0 .
b10011 -
b10011 ,
b0 +
b1 *
b0 )
1(
b0 '
b0 &
b0 %
b0 $
b0 #
1"
0!
$end
#5000
b100000 U
1!
#10000
0!
#15000
b100000 U
1!
#20000
0!
0"
#25000
b110011 ,
b11 )
b11 M
b10 '
b10 K
b10000000110110011 -
b10000000110110011 Y
b10 *
b10 H
b1 +
b1 J
b1 V
1!
#30000
0!
#35000
b100 )
b100 M
b11 '
b11 K
b11000001000110011 -
b11000001000110011 Y
b11 *
b11 H
b10 +
b10 J
b10 V
1!
#40000
0!
#45000
b101 )
b101 M
b100 '
b100 K
b100000001010110011 -
b100000001010110011 Y
b100 *
b100 H
b11 +
b11 J
b11 V
1!
#50000
0!
#55000
b110 )
b110 M
b101 '
b101 K
b101000001100110011 -
b101000001100110011 Y
b101 *
b101 H
b100 +
b100 J
b100 V
1!
#60000
0!
#65000
b111 )
b111 M
b110 '
b110 K
b110000001110110011 -
b110000001110110011 Y
b110 *
b110 H
b101 +
b101 J
b101 V
1!
#70000
0!
#75000
b1000 )
b1000 M
b111 '
b111 K
b111000010000110011 -
b111000010000110011 Y
b111 *
b111 H
b110 +
b110 J
b110 V
1!
#80000
0!
#85000
b1001 )
b1001 M
b1000 '
b1000 K
b1000000010010110011 -
b1000000010010110011 Y
b1000 *
b1000 H
b111 +
b111 J
b111 V
1!
#90000
0!
#95000
b1010 )
b1010 M
b1001 '
b1001 K
b1001000010100110011 -
b1001000010100110011 Y
b1001 *
b1001 H
b1000 +
b1000 J
b1000 V
1!
#100000
0!
#105000
b1011 )
b1011 M
b1010 '
b1010 K
b1010000010110110011 -
b1010000010110110011 Y
b1010 *
b1010 H
b1001 +
b1001 J
b1001 V
1!
#110000
0!
#115000
b1100 )
b1100 M
b1011 '
b1011 K
b1011000011000110011 -
b1011000011000110011 Y
b1011 *
b1011 H
b1010 +
b1010 J
b1010 V
1!
#120000
0!
#125000
b1101 )
b1101 M
b1100 '
b1100 K
b1100000011010110011 -
b1100000011010110011 Y
b1100 *
b1100 H
b1011 +
b1011 J
b1011 V
1!
#130000
0!
#135000
b1110 )
b1110 M
b1101 '
b1101 K
b1101000011100110011 -
b1101000011100110011 Y
b1101 *
b1101 H
b1100 +
b1100 J
b1100 V
1!
#140000
0!
#145000
b1111 )
b1111 M
b1110 '
b1110 K
b1110000011110110011 -
b1110000011110110011 Y
b1110 *
b1110 H
b1101 +
b1101 J
b1101 V
1!
#150000
0!
#155000
b10000 )
b10000 M
b1111 '
b1111 K
b1111000100000110011 -
b1111000100000110011 Y
b1111 *
b1111 H
b1110 +
b1110 J
b1110 V
1!
#160000
0!
#165000
b10001 )
b10001 M
b10000 '
b10000 K
b10000000100010110011 -
b10000000100010110011 Y
b0 *
b0 H
b1111 +
b1111 J
b1111 V
1!
#170000
0!
#175000
b10011 ,
b0 )
b0 M
b0 '
b0 K
b10011 -
b10011 Y
b1 *
b1 H
b0 +
b0 J
b0 V
1!
#180000
0!
#185000
b110011 ,
b11 )
b11 M
b10 '
b10 K
b10000000110110011 -
b10000000110110011 Y
b10 *
b10 H
b1 +
b1 J
b1 V
1!
#190000
0!
#195000
b100 )
b100 M
b11 '
b11 K
b11000001000110011 -
b11000001000110011 Y
b11 *
b11 H
b10 +
b10 J
b10 V
1!
#200000
0!
#205000
b101 )
b101 M
b100 '
b100 K
b100000001010110011 -
b100000001010110011 Y
b100 *
b100 H
b11 +
b11 J
b11 V
1!
#210000
0!
#215000
b110 )
b110 M
b101 '
b101 K
b101000001100110011 -
b101000001100110011 Y
b101 *
b101 H
b100 +
b100 J
b100 V
1!
